<?xml version="1.0" encoding="utf-8" ?>
<dwsync>
<file name="240-adjust.less" server="50.62.160.247/httpdocs/adventurehop/" local="130829793778764779" remote="130829746200000000" Dst="2" />
<file name="b-different-blue-gray.unpacked.less" server="50.62.160.247/httpdocs/adventurehop/" local="130829793778164778" remote="130829746200000000" Dst="2" />
<file name="b-different-blue-gray.min.less" server="50.62.160.247/httpdocs/adventurehop/" local="130829793777664777" remote="130829746200000000" Dst="2" />
<file name="b-different-blue-gray-variables-mixins.less" server="50.62.160.247/httpdocs/adventurehop/" local="130829793778664779" remote="130829746200000000" Dst="2" />
<file name="b-different-bw-variables-mixins.less" server="50.62.160.247/httpdocs/adventurehop/" local="130829793779864780" remote="130829746200000000" Dst="2" />
<file name="b-different-bw.min.less" server="50.62.160.247/httpdocs/adventurehop/" local="130829793778464779" remote="130829746200000000" Dst="2" />
<file name="b-different-bw.unpacked.less" server="50.62.160.247/httpdocs/adventurehop/" local="130829793780264781" remote="130829746200000000" Dst="2" />
<file name="b-different-green-gray.min.less" server="50.62.160.247/httpdocs/adventurehop/" local="130829793780764782" remote="130829746200000000" Dst="2" />
<file name="b-different-green-gray.unpacked.less" server="50.62.160.247/httpdocs/adventurehop/" local="130829793776264775" remote="130829746200000000" Dst="2" />
<file name="b-different-green-gray-variables-mixins.less" server="50.62.160.247/httpdocs/adventurehop/" local="130829793779064779" remote="130829746200000000" Dst="2" />
<file name="b-different-navy-taupe-variables-mixins.less" server="50.62.160.247/httpdocs/adventurehop/" local="130829793781864783" remote="130829746200000000" Dst="2" />
<file name="b-different-navy-taupe.min.less" server="50.62.160.247/httpdocs/adventurehop/" local="130829793777664777" remote="130829746200000000" Dst="2" />
<file name="b-different-navy-taupe.unpacked.less" server="50.62.160.247/httpdocs/adventurehop/" local="130829793776164775" remote="130829746200000000" Dst="2" />
<file name="b-different-navy-variables-mixins.less" server="50.62.160.247/httpdocs/adventurehop/" local="130829793781564783" remote="130829746200000000" Dst="2" />
<file name="b-different-navy.min.less" server="50.62.160.247/httpdocs/adventurehop/" local="130829793778564779" remote="130829746200000000" Dst="2" />
<file name="b-different-navy.unpacked.less" server="50.62.160.247/httpdocs/adventurehop/" local="130829793776964776" remote="130829746200000000" Dst="2" />
<file name="b-different-red-black-variables-mixins.less" server="50.62.160.247/httpdocs/adventurehop/" local="130829793781764783" remote="130829746200000000" Dst="2" />
<file name="b-different-red-black.min.less" server="50.62.160.247/httpdocs/adventurehop/" local="130829793777864778" remote="130829746200000000" Dst="2" />
<file name="b-different-red-black.unpacked.less" server="50.62.160.247/httpdocs/adventurehop/" local="130829793780964782" remote="130829746200000000" Dst="2" />
<file name="b-different-retro-variables-mixins.less" server="50.62.160.247/httpdocs/adventurehop/" local="130829793780464781" remote="130829746200000000" Dst="2" />
<file name="b-different-retro.min.less" server="50.62.160.247/httpdocs/adventurehop/" local="130829793776764776" remote="130829746200000000" Dst="2" />
<file name="b-different-retro.unpacked.less" server="50.62.160.247/httpdocs/adventurehop/" local="130829793780064781" remote="130829746200000000" Dst="2" />
<file name="b-different-salmon-blue.min.less" server="50.62.160.247/httpdocs/adventurehop/" local="130829793779564780" remote="130829746200000000" Dst="2" />
<file name="b-different-salmon-blue.unpacked.less" server="50.62.160.247/httpdocs/adventurehop/" local="130829793776564776" remote="130829746200000000" Dst="2" />
<file name="b-different-salmon-blue-variables-mixins.less" server="50.62.160.247/httpdocs/adventurehop/" local="130829793779664780" remote="130829746200000000" Dst="2" />
<file name="b-different-stone.min.less" server="50.62.160.247/httpdocs/adventurehop/" local="130829793777964778" remote="130829746800000000" Dst="2" />
<file name="b-different-stone.unpacked.less" server="50.62.160.247/httpdocs/adventurehop/" local="130829793777064777" remote="130829746800000000" Dst="2" />
<file name="b-different-stone-variables-mixins.less" server="50.62.160.247/httpdocs/adventurehop/" local="130829793778864779" remote="130829746800000000" Dst="2" />
<file name="b-different-white.min.less" server="50.62.160.247/httpdocs/adventurehop/" local="130829793779164779" remote="130829746800000000" Dst="2" />
<file name="b-different-white.unpacked.less" server="50.62.160.247/httpdocs/adventurehop/" local="130829793776464776" remote="130829746800000000" Dst="2" />
<file name="b-different-white-variables-mixins.less" server="50.62.160.247/httpdocs/adventurehop/" local="130829793779764780" remote="130829746800000000" Dst="2" />
<file name="blog.less" server="50.62.160.247/httpdocs/adventurehop/" local="130829793776064775" remote="130829746800000000" Dst="2" />
<file name="breadcrumb.less" server="50.62.160.247/httpdocs/adventurehop/" local="130829793781464783" remote="130829746800000000" Dst="2" />
<file name="bootstrap-components.less" server="50.62.160.247/httpdocs/adventurehop/" local="130829793779364780" remote="130829746800000000" Dst="2" />
<file name="call-to-action.less" server="50.62.160.247/httpdocs/adventurehop/" local="130829793778064778" remote="130829746800000000" Dst="2" />
<file name="click-slide.less" server="50.62.160.247/httpdocs/adventurehop/" local="130829793781564783" remote="130829746800000000" Dst="2" />
<file name="column-inner-featured-column.less" server="50.62.160.247/httpdocs/adventurehop/" local="130829793778964779" remote="130829746800000000" Dst="2" />
<file name="equal-style.less" server="50.62.160.247/httpdocs/adventurehop/" local="130829793781064782" remote="130829746800000000" Dst="2" />
<file name="footer.less" server="50.62.160.247/httpdocs/adventurehop/" local="130829793777564777" remote="130829746800000000" Dst="2" />
<file name="header-logo.less" server="50.62.160.247/httpdocs/adventurehop/" local="130829793776364776" remote="130829746800000000" Dst="2" />
<file name="html-body.less" server="50.62.160.247/httpdocs/adventurehop/" local="130829793776664776" remote="130829746800000000" Dst="2" />
<file name="images-figures.less" server="50.62.160.247/httpdocs/adventurehop/" local="130829793782064784" remote="130829746800000000" Dst="2" />
<file name="links-general-shared.less" server="50.62.160.247/httpdocs/adventurehop/" local="130829793779264780" remote="130829746800000000" Dst="2" />
<file name="magnific-popup.less" server="50.62.160.247/httpdocs/adventurehop/" local="130829793779464780" remote="130829746800000000" Dst="2" />
<file name="magpop-bu-keep" server="50.62.160.247/httpdocs/adventurehop/" local="130829793776764776" remote="130829746800000000" Dst="2" />
<file name="main-navigation.less" server="50.62.160.247/httpdocs/adventurehop/" local="130829793778164778" remote="130829746800000000" Dst="2" />
<file name="page-content-container.less" server="50.62.160.247/httpdocs/adventurehop/" local="130829793778364778" remote="130829746800000000" Dst="2" />
<file name="masonry-isotope-blog-portfolio-base.less" server="50.62.160.247/httpdocs/adventurehop/" local="130829793781664783" remote="130829746800000000" Dst="2" />
<file name="media-list.less" server="50.62.160.247/httpdocs/adventurehop/" local="130829793779964781" remote="130829746800000000" Dst="2" />
<file name="pricing-columns.less" server="50.62.160.247/httpdocs/adventurehop/" local="130829793777164777" remote="130829746800000000" Dst="2" />
<file name="slick-slider-base.less" server="50.62.160.247/httpdocs/adventurehop/" local="130829793777364777" remote="130829746800000000" Dst="2" />
<file name="page-header.less" server="50.62.160.247/httpdocs/adventurehop/" local="130829793777264777" remote="130829746800000000" Dst="2" />
<file name="slick-sliders-orig.less" server="50.62.160.247/httpdocs/adventurehop/" local="130829793781164782" remote="130829746800000000" Dst="2" />
<file name="slick-sliders.less" server="50.62.160.247/httpdocs/adventurehop/" local="130829793777164777" remote="130829746800000000" Dst="2" />
<file name="slide-panels.less" server="50.62.160.247/httpdocs/adventurehop/" local="130829793780664782" remote="130829746800000000" Dst="2" />
<file name="slide-to-sidebar.less" server="50.62.160.247/httpdocs/adventurehop/" local="130829793778264778" remote="130829746800000000" Dst="2" />
<file name="social-user-login-register.less" server="50.62.160.247/httpdocs/adventurehop/" local="130829793776864776" remote="130829746800000000" Dst="2" />
<file name="tabs-left.less" server="50.62.160.247/httpdocs/adventurehop/" local="130829793781364783" remote="130829746800000000" Dst="2" />
<file name="theme-showcase.less" server="50.62.160.247/httpdocs/adventurehop/" local="130829793781264782" remote="130829746800000000" Dst="2" />
<file name="theme.less" server="50.62.160.247/httpdocs/adventurehop/" local="130829793780564781" remote="130829746800000000" Dst="2" />
<file name="theme-info.less" server="50.62.160.247/httpdocs/adventurehop/" local="130829793777464777" remote="130829746800000000" Dst="2" />
<file name="typography.less" server="50.62.160.247/httpdocs/adventurehop/" local="130829793779664780" remote="130829746800000000" Dst="2" />
<file name="utility-classes.less" server="50.62.160.247/httpdocs/adventurehop/" local="130829793780264781" remote="130829746800000000" Dst="2" />
<file name="TOC.less" server="50.62.160.247/httpdocs/adventurehop/" local="130829793777764778" remote="130829746800000000" Dst="2" />
<file name="various-pages.less" server="50.62.160.247/httpdocs/adventurehop/" local="130829793778664779" remote="130829746800000000" Dst="2" />
<file name="video.less" server="50.62.160.247/httpdocs/adventurehop/" local="130829793780164781" remote="130829746800000000" Dst="2" />
<file name="widgets.less" server="50.62.160.247/httpdocs/adventurehop/" local="130829793780364781" remote="130829746800000000" Dst="2" />
</dwsync>